README.md
setup.cfg
setup.py
pandas_extensions/__init__.py
pandas_extensions/classes.py
pandas_extensions/functions.py
pandas_extensions.egg-info/PKG-INFO
pandas_extensions.egg-info/SOURCES.txt
pandas_extensions.egg-info/dependency_links.txt
pandas_extensions.egg-info/requires.txt
pandas_extensions.egg-info/top_level.txt
test/__init__.py
test/df_test.py