Metadata-Version: 2.1
Name: pandas-extensions
Version: 0.1
Summary: Extensions to the pandas package.
Home-page: https://github.com/bendevera/pandas_extensions.git
Author: Ben de Vera
Author-email: ben10devera@gmail.com
License: MIT
Keywords: data tools pandas
Platform: UNKNOWN
